redlock/__init__.py
redlock/cli.py
jc_redlock_py-1.0.8.dist-info/LICENSE.txt
jc_redlock_py-1.0.8.dist-info/METADATA
jc_redlock_py-1.0.8.dist-info/WHEEL
jc_redlock_py-1.0.8.dist-info/entry_points.txt
jc_redlock_py-1.0.8.dist-info/top_level.txt
jc_redlock_py-1.0.8.dist-info/RECORD
