Metadata-Version: 2.1
Name: jc-redlock-py
Version: 1.0.8
Summary: Redis locking mechanism
Home-page: https://github.com/SPSCommerce/identity-service
Author: pjdecoursey@spscommerce.com
Author-email: webapps@spscommerce.com
License: UNKNOWN
Platform: UNKNOWN
Classifier: Development Status :: 5 - Production/Stable
Classifier: Intended Audience :: Developers
Classifier: License :: OSI Approved :: MIT License
Classifier: Programming Language :: Python :: 2.6
Classifier: Programming Language :: Python :: 2.7
Classifier: Programming Language :: Python :: 3
Classifier: Programming Language :: Python :: 3.2
Classifier: Programming Language :: Python :: 3.3
Classifier: Programming Language :: Python :: 3.4
Requires-Dist: redis
